ntnx_aiops_py_client/__init__.py
ntnx_aiops_py_client/api_client.py
ntnx_aiops_py_client/api_response.py
ntnx_aiops_py_client/configuration.py
ntnx_aiops_py_client/custom_retry.py
ntnx_aiops_py_client/rest.py
ntnx_aiops_py_client/api/__init__.py
ntnx_aiops_py_client/api/scenarios_api.py
ntnx_aiops_py_client/api/stats_api.py
ntnx_aiops_py_client/models/__init__.py
ntnx_aiops_py_client/models/OneOfaiops/__init__.py
ntnx_aiops_py_client/models/OneOfaiops/v4/__init__.py
ntnx_aiops_py_client/models/OneOfaiops/v4/config/CreateScenarioApiResponsedata.py
ntnx_aiops_py_client/models/OneOfaiops/v4/config/CreateSimulationApiResponsedata.py
ntnx_aiops_py_client/models/OneOfaiops/v4/config/DeleteScenarioApiResponsedata.py
ntnx_aiops_py_client/models/OneOfaiops/v4/config/DeleteSimulationApiResponsedata.py
ntnx_aiops_py_client/models/OneOfaiops/v4/config/EntityDescriptorListApiResponsedata.py
ntnx_aiops_py_client/models/OneOfaiops/v4/config/EntityTypeListApiResponsedata.py
ntnx_aiops_py_client/models/OneOfaiops/v4/config/GenerateRecommendationApiResponsedata.py
ntnx_aiops_py_client/models/OneOfaiops/v4/config/GenerateReportApiResponsedata.py
ntnx_aiops_py_client/models/OneOfaiops/v4/config/GenerateRunwayApiResponsedata.py
ntnx_aiops_py_client/models/OneOfaiops/v4/config/GetScenarioApiResponsedata.py
ntnx_aiops_py_client/models/OneOfaiops/v4/config/GetScenarioReportApiResponsedata.py
ntnx_aiops_py_client/models/OneOfaiops/v4/config/GetSimulationApiResponsedata.py
ntnx_aiops_py_client/models/OneOfaiops/v4/config/ListScenariosApiResponsedata.py
ntnx_aiops_py_client/models/OneOfaiops/v4/config/ListSimulationsApiResponsedata.py
ntnx_aiops_py_client/models/OneOfaiops/v4/config/SourceListApiResponsedata.py
ntnx_aiops_py_client/models/OneOfaiops/v4/config/UpdateScenarioApiResponsedata.py
ntnx_aiops_py_client/models/OneOfaiops/v4/config/UpdateSimulationApiResponsedata.py
ntnx_aiops_py_client/models/OneOfaiops/v4/config/Workloadworkload_properties.py
ntnx_aiops_py_client-4.0.2.dist-info/LICENSE.txt
ntnx_aiops_py_client-4.0.2.dist-info/METADATA
ntnx_aiops_py_client-4.0.2.dist-info/WHEEL
ntnx_aiops_py_client-4.0.2.dist-info/top_level.txt
ntnx_aiops_py_client-4.0.2.dist-info/RECORD
